tweetsender/__init__.py
tweetsender/main.py
tweetsender/tweet.py
tweetsender/util.py
tweetsender-1.0.1.dist-info/DESCRIPTION.rst
tweetsender-1.0.1.dist-info/LICENSE.txt
tweetsender-1.0.1.dist-info/METADATA
tweetsender-1.0.1.dist-info/RECORD
tweetsender-1.0.1.dist-info/WHEEL
tweetsender-1.0.1.dist-info/entry_points.txt
tweetsender-1.0.1.dist-info/metadata.json
tweetsender-1.0.1.dist-info/top_level.txt
