Metadata-Version: 2.0
Name: tweetsender
Version: 1.0.1
Summary: Tweet-Only Twitter CLI
Home-page: https://github.com/Udomomo/tweetsender
Author: Naoya Otani
Author-email: batzuma@yahoo.co.jp
License: UNKNOWN
Platform: UNKNOWN
Requires-Dist: requests-oauthlib
Requires-Dist: python-dotenv
Requires-Dist: cliff
